hztrak/Polar Plotting.py
hztrak/__init__.py
hztrak/core.py
hztrak/habitability_calc.py
hztrak/plotting.py
hztrak-0.0.1.dist-info/licenses/LICENSE
hztrak-0.0.1.dist-info/METADATA
hztrak-0.0.1.dist-info/WHEEL
hztrak-0.0.1.dist-info/top_level.txt
hztrak-0.0.1.dist-info/RECORD
