Metadata-Version: 2.4
Name: hztrak
Version: 0.0.1
License-File: LICENSE
Requires-Dist: numpy
Requires-Dist: astroquery.ipac.nexsci.nasa_exoplanet_archive
Requires-Dist: astropy
Requires-Dist: pandas
Requires-Dist: matplotlib
Requires-Dist: pandas
Dynamic: license-file
